{
  "openapi": "3.0.0",
  "info": {
    "title": "Circle API",
    "description": "Welcome to Circle API!",
    "version": "1.0.0"
  },
  "servers": [
    {
      "url": "http://localhost:3000/"
    }
  ],
  "paths": {
    "/": {
      "get": {
        "description": "",
        "responses": {
          "200": {
            "description": "OK"
          }
        }
      },
      "post": {
        "description": "",
        "responses": {
          "200": {
            "description": "OK"
          }
        },
        "requestBody": {
          "content": {
            "application/json": {
              "schema": {
                "type": "object",
                "properties": {
                  "fullName": {
                    "example": "any"
                  },
                  "email": {
                    "example": "any"
                  },
                  "address": {
                    "example": "any"
                  }
                }
              }
            }
          }
        }
      },
      "patch": {
        "description": "",
        "responses": {
          "200": {
            "description": "OK"
          }
        }
      },
      "delete": {
        "description": "",
        "responses": {
          "200": {
            "description": "OK"
          }
        }
      }
    },
    "/auth/login": {
      "post": {
        "description": "",
        "responses": {
          "200": {
            "description": "OK"
          },
          "404": {
            "description": "Not Found"
          }
        },
        "requestBody": {
          "required": true,
          "content": {
            "application/json": {
              "schema": {
                "$ref": "#/components/schemas/LoginDTO"
              }
            }
          }
        }
      }
    },
    "/auth/register": {
      "post": {
        "description": "",
        "responses": {
          "200": {
            "description": "OK"
          }
        },
        "requestBody": {
          "required": true,
          "content": {
            "application/json": {
              "schema": {
                "$ref": "#/components/schemas/RegisterDTO"
              }
            }
          }
        }
      }
    },
    "/auth/check": {
      "post": {
        "description": "",
        "responses": {
          "200": {
            "description": "OK"
          },
          "401": {
            "description": "Unauthorized"
          }
        },
        "security": [
          {
            "bearerAuth": []
          }
        ]
      }
    },
    "/auth/forgot-password": {
      "post": {
        "description": "",
        "responses": {
          "200": {
            "description": "OK"
          }
        },
        "requestBody": {
          "required": true,
          "content": {
            "application/json": {
              "schema": {
                "$ref": "#/components/schemas/ForgotPasswordDTO"
              }
            }
          }
        }
      }
    },
    "/auth/reset-password": {
      "post": {
        "description": "",
        "responses": {
          "200": {
            "description": "OK"
          },
          "400": {
            "description": "Bad Request"
          },
          "401": {
            "description": "Unauthorized"
          },
          "404": {
            "description": "Not Found"
          }
        },
        "security": [
          {
            "bearerAuth": []
          }
        ],
        "requestBody": {
          "required": true,
          "content": {
            "application/json": {
              "schema": {
                "$ref": "#/components/schemas/ResetPasswordDTO"
              }
            }
          }
        }
      }
    },
    "/users/": {
      "get": {
        "description": "",
        "responses": {
          "200": {
            "description": "OK"
          }
        }
      },
      "post": {
        "description": "",
        "responses": {
          "200": {
            "description": "OK"
          }
        }
      }
    },
    "/users/{id}": {
      "get": {
        "description": "",
        "parameters": [
          {
            "name": "id",
            "in": "path",
            "required": true,
            "schema": {
              "type": "string"
            }
          }
        ],
        "responses": {
          "200": {
            "description": "OK"
          }
        }
      },
      "patch": {
        "description": "",
        "parameters": [
          {
            "name": "id",
            "in": "path",
            "required": true,
            "schema": {
              "type": "string"
            }
          }
        ],
        "responses": {
          "200": {
            "description": "OK"
          },
          "404": {
            "description": "Not Found"
          }
        }
      },
      "delete": {
        "description": "",
        "parameters": [
          {
            "name": "id",
            "in": "path",
            "required": true,
            "schema": {
              "type": "string"
            }
          }
        ],
        "responses": {
          "200": {
            "description": "OK"
          }
        }
      }
    },
    "/threads/": {
      "get": {
        "description": "",
        "responses": {
          "200": {
            "description": "OK"
          }
        }
      },
      "post": {
        "description": "",
        "responses": {
          "200": {
            "description": "OK"
          },
          "401": {
            "description": "Unauthorized"
          }
        },
        "security": [
          {
            "bearerAuth": []
          }
        ],
        "requestBody": {
          "required": true,
          "content": {
            "multipart/form-data": {
              "schema": {
                "$ref": "#/components/schemas/CreateThreadDTO"
              }
            }
          }
        }
      }
    },
    "/threads/{id}": {
      "get": {
        "description": "",
        "parameters": [
          {
            "name": "id",
            "in": "path",
            "required": true,
            "schema": {
              "type": "string"
            }
          }
        ],
        "responses": {
          "200": {
            "description": "OK"
          }
        }
      }
    }
  },
  "components": {
    "securitySchemes": {
      "bearerAuth": {
        "type": "http",
        "scheme": "bearer"
      }
    },
    "schemas": {
      "LoginDTO": {
        "type": "object",
        "properties": {
          "email": {
            "type": "string"
          },
          "password": {
            "type": "string"
          }
        }
      },
      "RegisterDTO": {
        "type": "object",
        "properties": {
          "fullName": {
            "type": "string"
          },
          "username": {
            "type": "string"
          },
          "email": {
            "type": "string"
          },
          "password": {
            "type": "string"
          }
        }
      },
      "ForgotPasswordDTO": {
        "type": "object",
        "properties": {
          "email": {
            "type": "string"
          }
        }
      },
      "ResetPasswordDTO": {
        "type": "object",
        "properties": {
          "oldPassword": {
            "type": "string"
          },
          "newPassword": {
            "type": "string"
          }
        }
      },
      "CreateThreadDTO": {
        "type": "object",
        "properties": {
          "content": {
            "type": "string"
          },
          "images": {
            "type": "file"
          }
        }
      }
    }
  }
}